stdplus/__init__.py
stdplus/_defaultify.py
stdplus/_fexecvp.py
stdplus/_fnmatches.py
stdplus/_isInt.py
stdplus/_isString.py
stdplus/_readfile.py
stdplus/_removeRoot.py
stdplus/_run_cmd.py
stdplus/_sshConfig.py
stdplus/_writefile.py
stdplus-0.0.47.dist-info/LICENSE
stdplus-0.0.47.dist-info/METADATA
stdplus-0.0.47.dist-info/WHEEL
stdplus-0.0.47.dist-info/entry_points.txt
stdplus-0.0.47.dist-info/top_level.txt
stdplus-0.0.47.dist-info/RECORD
