Metadata-Version: 2.1
Name: stdplus
Version: 0.0.47
Summary: A collection of utilities for python
Home-page: http://python.stdplus.org/
Author: Early Ehlinger
Author-email: earlye+stdplus@gmail.com
License: MIT
Keywords: libraries
Platform: UNKNOWN
Classifier: Development Status :: 3 - Alpha
Classifier: Intended Audience :: Developers
Classifier: Topic :: Software Development :: Libraries :: Python Modules
Classifier: License :: OSI Approved :: MIT License
Classifier: Programming Language :: Python :: 2
Classifier: Programming Language :: Python :: 2.7
Classifier: Programming Language :: Python :: 3
Classifier: Programming Language :: Python :: 3.8
Requires-Dist: pyperclip
Requires-Dist: joblib
Provides-Extra: dev
Requires-Dist: check-manifest; extra == 'dev'
Provides-Extra: test
Requires-Dist: coverage; extra == 'test'
